{
  "languageserver": {
    "efm": {
      "command": "efm-langserver",
      "args": [],
      // custom config path
      // "args": ["-c", "/path/to/your/config.yaml"],
      "filetypes": ["vim", "eruby", "markdown", "yaml"]
    },
    "flow": {
      "command": "flow",
      "args": ["lsp"],
      "filetypes": ["javascript", "javascriptreact"],
      "initializationOptions": {},
      "requireRootPattern": true,
      "settings": {},
      "rootPatterns": [".flowconfig"]
    }
  },
  "javascript.validate.enable": false,
  "tsserver.log": "verbose",
  "tsserver.npm": "/Users/brandoncc/.nvm/versions/node/v10.22.0/bin/npm",
  "coc.preferences.formatOnSaveFiletypes": [
    "javascript",
    "javascriptreact",
    "typescript",
    "typescriptreact"
  ],
  "cSpell.userWords": [
    "Airtable",
    "Avenir",
    "CSRF",
    "Dragula",
    "Focusable",
    "Rollbar",
    "Viewbox",
    "autoscroller",
    "bpry",
    "droppable",
    "exif",
    "filestack",
    "flexbox",
    "gundo",
    "jremmen",
    "junegunn",
    "neoclide",
    "semistandard",
    "shopify",
    "tealeaf",
    "tpope",
    "trusktr",
    "xargs"
  ],
  "codeLens.enable": true,
  "git.addGBlameToVirtualText": true,
  "solargraph.diagnostics": true,
  // don't change working directory when changing tree directory
  "explorer.file.tabCD": false,
  "explorer.quitOnOpen": true,
  "explorer.icon.enableNerdfont": true,
  "explorer.openAction.strategy": "split",
  "explorer.icon.enableVimDevicons": true,
  "explorer.previewAction.onHover": false,
  "explorer.datetime.format": "MM/dd/yy HH:mm:ss",
  "explorer.file.column.git.showIgnored": true,
  "lua.diagnostics.disable" : [
    "lowercase-global"
  ]
}
